setup.py
Logr.egg-info/PKG-INFO
Logr.egg-info/SOURCES.txt
Logr.egg-info/dependency_links.txt
Logr.egg-info/top_level.txt
logr/__init__.py