Metadata-Version: 1.1
Name: Logr
Version: 0.2.1
Summary: Simple python logging wrapper
Home-page: http://github.com/fuzeman/Logr
Author: Dean Gardiner
Author-email: gardiner91@gmail.com
License: UNKNOWN
Platform: UNKNOWN
Classifier: Programming Language :: Python
Classifier: License :: OSI Approved :: GNU General Public License v3 or later (GPLv3+)
Classifier: Operating System :: OS Independent
Classifier: Environment :: Other Environment
Classifier: Intended Audience :: Developers
Classifier: Topic :: Software Development :: Libraries :: Python Modules
Classifier: Topic :: System :: Logging
